odoo/addons/stock_measuring_device_zippcube/README.rst
odoo/addons/stock_measuring_device_zippcube/__init__.py
odoo/addons/stock_measuring_device_zippcube/__manifest__.py
odoo/addons/stock_measuring_device_zippcube/components/__init__.py
odoo/addons/stock_measuring_device_zippcube/components/zippcube_device_component.py
odoo/addons/stock_measuring_device_zippcube/controllers/__init__.py
odoo/addons/stock_measuring_device_zippcube/controllers/main.py
odoo/addons/stock_measuring_device_zippcube/i18n/stock_measuring_device_zippcube.pot
odoo/addons/stock_measuring_device_zippcube/models/__init__.py
odoo/addons/stock_measuring_device_zippcube/models/measuring_device.py
odoo/addons/stock_measuring_device_zippcube/readme/CONFIGURE.rst
odoo/addons/stock_measuring_device_zippcube/readme/CONTRIBUTORS.rst
odoo/addons/stock_measuring_device_zippcube/readme/CREDITS.rst
odoo/addons/stock_measuring_device_zippcube/readme/DESCRIPTION.rst
odoo/addons/stock_measuring_device_zippcube/readme/INSTALL.rst
odoo/addons/stock_measuring_device_zippcube/readme/ROADMAP.rst
odoo/addons/stock_measuring_device_zippcube/readme/USAGE.rst
odoo/addons/stock_measuring_device_zippcube/scripts/measurement.sh
odoo/addons/stock_measuring_device_zippcube/static/description/icon.png
odoo/addons/stock_measuring_device_zippcube/static/description/index.html
odoo/addons/stock_measuring_device_zippcube/tests/__init__.py
odoo/addons/stock_measuring_device_zippcube/tests/test_zippcube_wizard.py
odoo14_addon_stock_measuring_device_zippcube-14.0.1.0.1.dist-info/METADATA
odoo14_addon_stock_measuring_device_zippcube-14.0.1.0.1.dist-info/WHEEL
odoo14_addon_stock_measuring_device_zippcube-14.0.1.0.1.dist-info/top_level.txt
odoo14_addon_stock_measuring_device_zippcube-14.0.1.0.1.dist-info/RECORD
